{
  "display": {
    "icon": {
      "item": "modogs:beagle_spawn_egg"
    },
    "title": "Beagle Breeder",
    "description": "Breed a Beagle",
    "frame": "task",
    "show_toast": true,
    "announce_to_chat": true
  },
  "parent": "modogs:b_dogs/tame_beagle",
  "criteria": {
    "requirement": {
      "trigger": "minecraft:bred_animals",
      "conditions": {
        "child": [
          {
            "condition": "minecraft:entity_properties",
            "entity": "this",
            "predicate": {
              "type": "modogs:beagle"
            }
          }
        ]
      }
    }
  }
}